[{"dist": 5.2, "zip": "00840"},{"dist": 8.0, "zip": "00820"},{"dist": 39.4, "zip": "00830"},{"dist": 41.4, "zip": "00802"},{"dist": 64.0, "zip": "00735"},{"dist": 66.2, "zip": "00740"},{"dist": 67.2, "zip": "00738"},{"dist": 67.4, "zip": "00741"},{"dist": 67.4, "zip": "00718"},{"dist": 70.4, "zip": "00791"},{"dist": 71.6, "zip": "00767"},{"dist": 72.0, "zip": "00773"},{"dist": 72.9, "zip": "00707"},{"dist": 74.2, "zip": "00771"},{"dist": 78.3, "zip": "00777"},{"dist": 78.9, "zip": "00745"},{"dist": 79.9, "zip": "00723"},{"dist": 80.4, "zip": "00765"},{"dist": 80.5, "zip": "00754"},{"dist": 82.5, "zip": "00729"},{"dist": 82.7, "zip": "00778"},{"dist": 82.8, "zip": "00714"},{"dist": 83.5, "zip": "00772"},{"dist": 85.8, "zip": "00727"},{"dist": 85.8, "zip": "00725"},{"dist": 86.0, "zip": "00784"},{"dist": 88.0, "zip": "00979"},{"dist": 88.0, "zip": "00982"},{"dist": 88.0, "zip": "00983"},{"dist": 88.0, "zip": "00987"},{"dist": 88.0, "zip": "00985"},{"dist": 88.4, "zip": "00976"},{"dist": 90.6, "zip": "00703"},{"dist": 91.3, "zip": "00736"},{"dist": 91.8, "zip": "00739"},{"dist": 92.6, "zip": "00920"},{"dist": 92.6, "zip": "00921"},{"dist": 92.6, "zip": "00923"},{"dist": 92.6, "zip": "00924"},{"dist": 92.6, "zip": "00925"},{"dist": 92.6, "zip": "00927"},{"dist": 92.6, "zip": "00975"},{"dist": 92.6, "zip": "00926"},{"dist": 92.6, "zip": "00939"},{"dist": 92.6, "zip": "00918"},{"dist": 92.6, "zip": "00917"},{"dist": 92.6, "zip": "00915"},{"dist": 92.6, "zip": "00935"},{"dist": 92.6, "zip": "00901"},{"dist": 92.6, "zip": "00907"},{"dist": 92.6, "zip": "00911"},{"dist": 92.6, "zip": "00912"},{"dist": 92.6, "zip": "00913"},{"dist": 93.0, "zip": "00704"},{"dist": 93.2, "zip": "00957"},{"dist": 93.2, "zip": "00959"},{"dist": 93.2, "zip": "00956"},{"dist": 94.0, "zip": "00909"},{"dist": 94.9, "zip": "00966"},{"dist": 94.9, "zip": "00965"},{"dist": 94.9, "zip": "00971"},{"dist": 94.9, "zip": "00969"},{"dist": 94.9, "zip": "00968"},{"dist": 95.8, "zip": "00934"},{"dist": 96.5, "zip": "00962"},{"dist": 97.3, "zip": "00782"},{"dist": 97.7, "zip": "00751"},{"dist": 98.2, "zip": "00705"},{"dist": 98.2, "zip": "00961"}]
