[{"dist": 3.4, "zip": "13664"},{"dist": 6.9, "zip": "13646"},{"dist": 13.3, "zip": "13633"},{"dist": 14.6, "zip": "13654"},{"dist": 15.1, "zip": "13669"},{"dist": 15.8, "zip": "13679"},{"dist": 16.9, "zip": "13681"},{"dist": 18.0, "zip": "13680"},{"dist": 18.1, "zip": "13640"},{"dist": 18.1, "zip": "13642"},{"dist": 18.4, "zip": "13607"},{"dist": 19.2, "zip": "13630"},{"dist": 20.2, "zip": "13675"},{"dist": 22.8, "zip": "13652"},{"dist": 23.4, "zip": "13691"},{"dist": 24.1, "zip": "13658"},{"dist": 24.5, "zip": "13608"},{"dist": 25.3, "zip": "13617"},{"dist": 26.1, "zip": "13635"},{"dist": 26.9, "zip": "13673"},{"dist": 28.2, "zip": "13656"},{"dist": 29.1, "zip": "13624"},{"dist": 29.8, "zip": "13660"},{"dist": 32.2, "zip": "13694"},{"dist": 32.3, "zip": "13637"},{"dist": 32.3, "zip": "13648"},{"dist": 32.8, "zip": "13665"},{"dist": 33.7, "zip": "13639"},{"dist": 33.9, "zip": "13684"},{"dist": 34.1, "zip": "13602"},{"dist": 35.4, "zip": "13699"},{"dist": 35.4, "zip": "13676"},{"dist": 36.1, "zip": "13616"},{"dist": 36.6, "zip": "13668"},{"dist": 36.7, "zip": "13638"},{"dist": 37.2, "zip": "13621"},{"dist": 37.7, "zip": "13612"},{"dist": 38.8, "zip": "13667"},{"dist": 38.9, "zip": "13619"},{"dist": 39.0, "zip": "13670"},{"dist": 39.5, "zip": "13687"},{"dist": 39.9, "zip": "13622"},{"dist": 41.0, "zip": "13603"},{"dist": 41.0, "zip": "13601"},{"dist": 41.3, "zip": "13634"},{"dist": 41.4, "zip": "13696"},{"dist": 41.5, "zip": "13690"},{"dist": 42.7, "zip": "13672"},{"dist": 43.3, "zip": "13618"},{"dist": 44.9, "zip": "13626"},{"dist": 45.0, "zip": "13625"},{"dist": 45.4, "zip": "13697"},{"dist": 46.3, "zip": "13620"},{"dist": 46.8, "zip": "13685"},{"dist": 46.8, "zip": "13662"},{"dist": 47.1, "zip": "13327"},{"dist": 47.2, "zip": "13613"},{"dist": 47.3, "zip": "13693"},{"dist": 50.1, "zip": "13606"},{"dist": 50.8, "zip": "13682"},{"dist": 52.0, "zip": "12965"},{"dist": 52.8, "zip": "12967"},{"dist": 53.0, "zip": "12949"},{"dist": 53.0, "zip": "12922"},{"dist": 53.4, "zip": "13367"},{"dist": 53.8, "zip": "13605"},{"dist": 55.9, "zip": "13659"},{"dist": 56.7, "zip": "12980"},{"dist": 57.0, "zip": "13650"},{"dist": 57.7, "zip": "12930"},{"dist": 58.8, "zip": "12957"},{"dist": 59.4, "zip": "13655"},{"dist": 59.9, "zip": "12914"},{"dist": 60.2, "zip": "13636"},{"dist": 60.3, "zip": "13343"},{"dist": 60.3, "zip": "13661"},{"dist": 60.8, "zip": "12916"},{"dist": 62.1, "zip": "13345"},{"dist": 63.9, "zip": "12986"},{"dist": 64.7, "zip": "12966"},{"dist": 64.9, "zip": "13083"},{"dist": 65.0, "zip": "13473"},{"dist": 65.2, "zip": "13145"},{"dist": 65.9, "zip": "13437"},{"dist": 66.1, "zip": "13368"},{"dist": 66.6, "zip": "12937"},{"dist": 67.2, "zip": "13420"},{"dist": 68.4, "zip": "13433"},{"dist": 68.5, "zip": "13144"},{"dist": 68.7, "zip": "13331"},{"dist": 68.9, "zip": "13325"},{"dist": 70.8, "zip": "12970"},{"dist": 71.1, "zip": "13142"},{"dist": 71.3, "zip": "12953"},{"dist": 71.6, "zip": "12945"},{"dist": 71.7, "zip": "13436"},{"dist": 72.9, "zip": "13302"},{"dist": 73.6, "zip": "13360"},{"dist": 73.7, "zip": "12847"},{"dist": 73.8, "zip": "12926"},{"dist": 75.0, "zip": "13489"},{"dist": 75.2, "zip": "13309"},{"dist": 75.2, "zip": "13494"},{"dist": 76.9, "zip": "12812"},{"dist": 77.9, "zip": "12983"},{"dist": 78.0, "zip": "13493"},{"dist": 78.1, "zip": "12917"},{"dist": 78.3, "zip": "12989"},{"dist": 78.3, "zip": "12913"},{"dist": 78.7, "zip": "13303"},{"dist": 79.4, "zip": "13114"},{"dist": 79.5, "zip": "12969"},{"dist": 79.6, "zip": "13338"},{"dist": 80.4, "zip": "13483"},{"dist": 80.6, "zip": "13301"},{"dist": 81.7, "zip": "13131"},{"dist": 82.8, "zip": "12920"},{"dist": 83.6, "zip": "13316"},{"dist": 84.4, "zip": "12879"},{"dist": 84.4, "zip": "12852"},{"dist": 85.2, "zip": "13103"},{"dist": 85.4, "zip": "13076"},{"dist": 85.6, "zip": "13126"},{"dist": 85.7, "zip": "13471"},{"dist": 85.7, "zip": "12946"},{"dist": 86.0, "zip": "13363"},{"dist": 86.9, "zip": "13486"},{"dist": 87.2, "zip": "13028"},{"dist": 87.4, "zip": "12952"},{"dist": 87.4, "zip": "12955"},{"dist": 87.7, "zip": "13308"},{"dist": 87.8, "zip": "12842"},{"dist": 87.8, "zip": "13438"},{"dist": 88.5, "zip": "13167"},{"dist": 90.0, "zip": "13036"},{"dist": 90.5, "zip": "13044"},{"dist": 90.8, "zip": "12923"},{"dist": 91.0, "zip": "13042"},{"dist": 91.1, "zip": "13304"},{"dist": 91.9, "zip": "12934"},{"dist": 91.9, "zip": "12981"},{"dist": 92.3, "zip": "12997"},{"dist": 92.3, "zip": "12108"},{"dist": 92.3, "zip": "13354"},{"dist": 92.4, "zip": "13440"},{"dist": 92.4, "zip": "13441"},{"dist": 92.4, "zip": "13069"},{"dist": 92.4, "zip": "13449"},{"dist": 92.5, "zip": "12164"},{"dist": 92.6, "zip": "12978"},{"dist": 92.7, "zip": "13132"},{"dist": 92.9, "zip": "12857"},{"dist": 93.3, "zip": "13469"},{"dist": 93.3, "zip": "13029"},{"dist": 93.7, "zip": "12912"},{"dist": 94.8, "zip": "12987"},{"dist": 95.0, "zip": "12985"},{"dist": 95.4, "zip": "13324"},{"dist": 95.4, "zip": "13135"},{"dist": 95.5, "zip": "12935"},{"dist": 95.8, "zip": "13074"},{"dist": 95.8, "zip": "12942"},{"dist": 96.1, "zip": "12139"},{"dist": 96.2, "zip": "13431"},{"dist": 96.6, "zip": "13403"},{"dist": 96.7, "zip": "12943"},{"dist": 96.8, "zip": "13156"},{"dist": 97.0, "zip": "13039"},{"dist": 97.0, "zip": "13041"},{"dist": 97.5, "zip": "13478"},{"dist": 97.5, "zip": "13424"},{"dist": 98.0, "zip": "13054"},{"dist": 98.0, "zip": "12941"},{"dist": 98.7, "zip": "12918"},{"dist": 98.8, "zip": "13111"},{"dist": 99.6, "zip": "12851"},{"dist": 99.6, "zip": "13416"},{"dist": 99.7, "zip": "13490"},{"dist": 99.9, "zip": "13492"}]
