[{"dist": 8.3, "zip": "50238"},{"dist": 12.7, "zip": "50150"},{"dist": 12.8, "zip": "52531"},{"dist": 13.5, "zip": "52571"},{"dist": 13.7, "zip": "50049"},{"dist": 14.9, "zip": "50057"},{"dist": 15.0, "zip": "50116"},{"dist": 15.4, "zip": "52574"},{"dist": 15.9, "zip": "52581"},{"dist": 16.7, "zip": "50165"},{"dist": 17.3, "zip": "50044"},{"dist": 17.5, "zip": "52583"},{"dist": 19.3, "zip": "50062"},{"dist": 19.4, "zip": "52544"},{"dist": 20.9, "zip": "52593"},{"dist": 21.1, "zip": "52590"},{"dist": 21.2, "zip": "50060"},{"dist": 21.4, "zip": "52536"},{"dist": 21.7, "zip": "52594"},{"dist": 21.8, "zip": "50068"},{"dist": 22.2, "zip": "50151"},{"dist": 22.4, "zip": "50139"},{"dist": 22.5, "zip": "50256"},{"dist": 23.0, "zip": "50138"},{"dist": 23.6, "zip": "50119"},{"dist": 24.8, "zip": "52553"},{"dist": 24.9, "zip": "50123"},{"dist": 25.0, "zip": "52549"},{"dist": 25.6, "zip": "50008"},{"dist": 25.7, "zip": "52555"},{"dist": 27.4, "zip": "52534"},{"dist": 27.7, "zip": "50143"},{"dist": 28.0, "zip": "52548"},{"dist": 28.3, "zip": "52572"},{"dist": 28.7, "zip": "50275"},{"dist": 29.0, "zip": "50166"},{"dist": 29.8, "zip": "50219"},{"dist": 29.9, "zip": "50225"},{"dist": 30.2, "zip": "52566"},{"dist": 30.2, "zip": "52577"},{"dist": 31.2, "zip": "50103"},{"dist": 31.9, "zip": "52543"},{"dist": 32.0, "zip": "52552"},{"dist": 32.3, "zip": "50052"},{"dist": 32.5, "zip": "50214"},{"dist": 32.9, "zip": "52501"},{"dist": 33.3, "zip": "64672"},{"dist": 34.5, "zip": "50001"},{"dist": 35.0, "zip": "63535"},{"dist": 35.3, "zip": "63565"},{"dist": 35.5, "zip": "52561"},{"dist": 35.8, "zip": "50252"},{"dist": 36.5, "zip": "50264"},{"dist": 36.8, "zip": "52537"},{"dist": 37.3, "zip": "50147"},{"dist": 37.4, "zip": "50170"},{"dist": 37.5, "zip": "50118"},{"dist": 37.7, "zip": "50125"},{"dist": 38.0, "zip": "52560"},{"dist": 38.2, "zip": "64655"},{"dist": 38.2, "zip": "52586"},{"dist": 38.2, "zip": "50213"},{"dist": 38.5, "zip": "63551"},{"dist": 38.5, "zip": "50210"},{"dist": 38.6, "zip": "52530"},{"dist": 39.4, "zip": "50207"},{"dist": 39.9, "zip": "50262"},{"dist": 40.0, "zip": "50237"},{"dist": 40.2, "zip": "63541"},{"dist": 40.6, "zip": "50144"},{"dist": 40.7, "zip": "50232"},{"dist": 40.7, "zip": "52563"},{"dist": 41.0, "zip": "64661"},{"dist": 41.5, "zip": "63548"},{"dist": 42.0, "zip": "50251"},{"dist": 42.9, "zip": "50153"},{"dist": 43.1, "zip": "50047"},{"dist": 43.3, "zip": "50228"},{"dist": 43.5, "zip": "63560"},{"dist": 43.6, "zip": "52554"},{"dist": 44.2, "zip": "52550"},{"dist": 44.3, "zip": "63567"},{"dist": 44.4, "zip": "50242"},{"dist": 44.4, "zip": "50067"},{"dist": 44.6, "zip": "50240"},{"dist": 44.6, "zip": "50257"},{"dist": 44.8, "zip": "64667"},{"dist": 44.9, "zip": "52584"},{"dist": 45.3, "zip": "50229"},{"dist": 45.9, "zip": "52533"},{"dist": 46.1, "zip": "50268"},{"dist": 46.4, "zip": "63561"},{"dist": 46.6, "zip": "50065"},{"dist": 46.6, "zip": "50033"},{"dist": 46.9, "zip": "50027"},{"dist": 47.1, "zip": "50174"},{"dist": 47.2, "zip": "52588"},{"dist": 47.6, "zip": "50327"},{"dist": 48.3, "zip": "50104"},{"dist": 48.4, "zip": "50211"},{"dist": 48.8, "zip": "50054"},{"dist": 49.0, "zip": "50208"},{"dist": 49.4, "zip": "50171"},{"dist": 49.4, "zip": "50108"},{"dist": 49.6, "zip": "63536"},{"dist": 49.6, "zip": "64673"},{"dist": 49.7, "zip": "64645"},{"dist": 49.7, "zip": "50222"},{"dist": 49.8, "zip": "50169"},{"dist": 49.9, "zip": "52591"},{"dist": 49.9, "zip": "63545"},{"dist": 50.2, "zip": "63546"},{"dist": 50.3, "zip": "50391"},{"dist": 50.3, "zip": "50381"},{"dist": 50.3, "zip": "50380"},{"dist": 50.3, "zip": "50369"},{"dist": 50.3, "zip": "50367"},{"dist": 50.3, "zip": "50364"},{"dist": 50.3, "zip": "50363"},{"dist": 50.3, "zip": "50362"},{"dist": 50.3, "zip": "50392"},{"dist": 50.3, "zip": "50395"},{"dist": 50.3, "zip": "50981"},{"dist": 50.3, "zip": "50980"},{"dist": 50.3, "zip": "50361"},{"dist": 50.3, "zip": "50947"},{"dist": 50.3, "zip": "50940"},{"dist": 50.3, "zip": "50936"},{"dist": 50.3, "zip": "50310"},{"dist": 50.3, "zip": "50396"},{"dist": 50.3, "zip": "50950"},{"dist": 50.3, "zip": "50360"},{"dist": 50.3, "zip": "50320"},{"dist": 50.3, "zip": "50307"},{"dist": 50.3, "zip": "50308"},{"dist": 50.3, "zip": "50309"},{"dist": 50.3, "zip": "50311"},{"dist": 50.3, "zip": "50319"},{"dist": 50.3, "zip": "50317"},{"dist": 50.3, "zip": "50312"},{"dist": 50.3, "zip": "50316"},{"dist": 50.3, "zip": "50315"},{"dist": 50.3, "zip": "50314"},{"dist": 50.3, "zip": "50321"},{"dist": 50.3, "zip": "50313"},{"dist": 50.3, "zip": "50330"},{"dist": 50.3, "zip": "50329"},{"dist": 50.3, "zip": "50328"},{"dist": 50.3, "zip": "50332"},{"dist": 50.3, "zip": "50334"},{"dist": 50.3, "zip": "50335"},{"dist": 50.3, "zip": "50336"},{"dist": 50.3, "zip": "50339"},{"dist": 50.3, "zip": "50359"},{"dist": 50.3, "zip": "50331"},{"dist": 50.5, "zip": "63544"},{"dist": 50.7, "zip": "52570"},{"dist": 50.9, "zip": "50061"},{"dist": 50.9, "zip": "50135"},{"dist": 51.0, "zip": "52580"},{"dist": 51.4, "zip": "50009"},{"dist": 51.5, "zip": "50982"},{"dist": 51.5, "zip": "52576"},{"dist": 51.9, "zip": "50983"},{"dist": 52.2, "zip": "50254"},{"dist": 52.2, "zip": "52567"},{"dist": 52.2, "zip": "50127"},{"dist": 52.7, "zip": "50140"},{"dist": 53.0, "zip": "50035"},{"dist": 53.1, "zip": "50136"},{"dist": 53.4, "zip": "64632"},{"dist": 53.5, "zip": "50149"},{"dist": 53.7, "zip": "52551"},{"dist": 54.0, "zip": "63556"},{"dist": 54.1, "zip": "52222"},{"dist": 54.8, "zip": "52355"},{"dist": 54.8, "zip": "63559"},{"dist": 54.9, "zip": "50265"},{"dist": 54.9, "zip": "50266"},{"dist": 54.9, "zip": "50398"},{"dist": 55.0, "zip": "50112"},{"dist": 55.1, "zip": "50324"},{"dist": 55.3, "zip": "50168"},{"dist": 55.5, "zip": "50133"},{"dist": 55.8, "zip": "50157"},{"dist": 55.9, "zip": "50273"},{"dist": 56.1, "zip": "50074"},{"dist": 56.3, "zip": "52556"},{"dist": 56.3, "zip": "52557"},{"dist": 56.3, "zip": "52542"},{"dist": 56.4, "zip": "52585"},{"dist": 56.8, "zip": "50325"},{"dist": 57.7, "zip": "50323"},{"dist": 57.7, "zip": "50322"},{"dist": 57.8, "zip": "50038"},{"dist": 57.8, "zip": "52231"},{"dist": 57.9, "zip": "52535"},{"dist": 58.0, "zip": "64426"},{"dist": 58.3, "zip": "52221"},{"dist": 58.3, "zip": "50028"},{"dist": 58.4, "zip": "63555"},{"dist": 58.7, "zip": "64679"},{"dist": 58.7, "zip": "50023"},{"dist": 58.8, "zip": "50021"},{"dist": 59.0, "zip": "52565"},{"dist": 59.1, "zip": "52335"},{"dist": 59.2, "zip": "50131"},{"dist": 59.9, "zip": "63501"},{"dist": 60.0, "zip": "50830"},{"dist": 60.4, "zip": "52211"},{"dist": 60.4, "zip": "50263"},{"dist": 60.6, "zip": "50261"},{"dist": 60.6, "zip": "50111"},{"dist": 60.7, "zip": "50863"},{"dist": 60.9, "zip": "64442"},{"dist": 61.0, "zip": "50073"},{"dist": 61.0, "zip": "64646"},{"dist": 61.4, "zip": "50155"},{"dist": 62.0, "zip": "64641"},{"dist": 62.2, "zip": "52316"},{"dist": 62.4, "zip": "52248"},{"dist": 62.5, "zip": "50141"},{"dist": 62.7, "zip": "50069"},{"dist": 62.8, "zip": "64481"},{"dist": 62.9, "zip": "50106"},{"dist": 63.4, "zip": "52573"},{"dist": 63.8, "zip": "52651"},{"dist": 63.9, "zip": "50861"},{"dist": 64.5, "zip": "50007"},{"dist": 64.6, "zip": "63566"},{"dist": 64.7, "zip": "52347"},{"dist": 64.7, "zip": "50226"},{"dist": 64.8, "zip": "52540"},{"dist": 64.8, "zip": "63432"},{"dist": 64.9, "zip": "50854"},{"dist": 64.9, "zip": "50055"},{"dist": 65.3, "zip": "50234"},{"dist": 65.4, "zip": "50161"},{"dist": 65.8, "zip": "64458"},{"dist": 65.9, "zip": "64630"},{"dist": 66.1, "zip": "52232"},{"dist": 66.2, "zip": "50072"},{"dist": 66.4, "zip": "50162"},{"dist": 66.4, "zip": "50120"},{"dist": 66.5, "zip": "63442"},{"dist": 66.9, "zip": "50003"},{"dist": 67.3, "zip": "50109"},{"dist": 67.4, "zip": "63531"},{"dist": 67.6, "zip": "52620"},{"dist": 67.8, "zip": "50046"},{"dist": 67.8, "zip": "63533"},{"dist": 67.8, "zip": "52635"},{"dist": 68.0, "zip": "52325"},{"dist": 68.3, "zip": "63563"},{"dist": 68.6, "zip": "52359"},{"dist": 68.6, "zip": "50063"},{"dist": 68.7, "zip": "64683"},{"dist": 68.9, "zip": "50845"},{"dist": 68.9, "zip": "50801"},{"dist": 69.2, "zip": "63547"},{"dist": 69.2, "zip": "50124"},{"dist": 69.4, "zip": "52251"},{"dist": 69.5, "zip": "64652"},{"dist": 69.7, "zip": "63543"},{"dist": 69.8, "zip": "63540"},{"dist": 70.2, "zip": "52630"},{"dist": 70.4, "zip": "50244"},{"dist": 70.9, "zip": "63453"},{"dist": 71.0, "zip": "52356"},{"dist": 71.1, "zip": "50835"},{"dist": 71.1, "zip": "50173"},{"dist": 71.4, "zip": "50247"},{"dist": 71.4, "zip": "64467"},{"dist": 71.4, "zip": "64674"},{"dist": 71.4, "zip": "50070"},{"dist": 71.4, "zip": "63474"},{"dist": 71.5, "zip": "64424"},{"dist": 71.5, "zip": "52361"},{"dist": 71.6, "zip": "63557"},{"dist": 71.9, "zip": "52339"},{"dist": 72.3, "zip": "63549"},{"dist": 72.5, "zip": "50056"},{"dist": 72.6, "zip": "52626"},{"dist": 72.7, "zip": "63537"},{"dist": 72.8, "zip": "50158"},{"dist": 72.9, "zip": "50858"},{"dist": 73.0, "zip": "50233"},{"dist": 73.1, "zip": "52215"},{"dist": 73.1, "zip": "64642"},{"dist": 73.2, "zip": "52654"},{"dist": 73.2, "zip": "50156"},{"dist": 73.4, "zip": "52353"},{"dist": 73.5, "zip": "50167"},{"dist": 73.7, "zip": "52342"},{"dist": 74.1, "zip": "50842"},{"dist": 74.2, "zip": "63538"},{"dist": 74.2, "zip": "50201"},{"dist": 74.3, "zip": "50134"},{"dist": 74.4, "zip": "52208"},{"dist": 74.6, "zip": "52649"},{"dist": 74.8, "zip": "50860"},{"dist": 75.1, "zip": "50250"},{"dist": 75.4, "zip": "50276"},{"dist": 75.5, "zip": "52301"},{"dist": 75.7, "zip": "50840"},{"dist": 76.6, "zip": "50849"},{"dist": 76.6, "zip": "64635"},{"dist": 76.9, "zip": "63539"},{"dist": 77.0, "zip": "64653"},{"dist": 77.6, "zip": "52257"},{"dist": 77.7, "zip": "52247"},{"dist": 77.8, "zip": "50014"},{"dist": 77.8, "zip": "50012"},{"dist": 77.8, "zip": "50011"},{"dist": 77.8, "zip": "50010"},{"dist": 77.8, "zip": "50013"},{"dist": 78.1, "zip": "64471"},{"dist": 78.1, "zip": "50005"},{"dist": 78.2, "zip": "52641"},{"dist": 78.2, "zip": "50051"},{"dist": 78.3, "zip": "50039"},{"dist": 78.4, "zip": "50146"},{"dist": 78.4, "zip": "64441"},{"dist": 78.6, "zip": "52334"},{"dist": 78.9, "zip": "64636"},{"dist": 79.0, "zip": "50632"},{"dist": 79.0, "zip": "50836"},{"dist": 79.1, "zip": "50239"},{"dist": 79.1, "zip": "50851"},{"dist": 79.3, "zip": "63446"},{"dist": 79.3, "zip": "63465"},{"dist": 79.6, "zip": "64456"},{"dist": 79.6, "zip": "63445"},{"dist": 79.8, "zip": "50164"},{"dist": 79.9, "zip": "52225"},{"dist": 80.2, "zip": "52621"},{"dist": 80.2, "zip": "63460"},{"dist": 80.4, "zip": "64648"},{"dist": 80.4, "zip": "52201"},{"dist": 80.5, "zip": "50220"},{"dist": 80.6, "zip": "52209"},{"dist": 80.8, "zip": "52625"},{"dist": 81.0, "zip": "63530"},{"dist": 81.3, "zip": "52657"},{"dist": 81.5, "zip": "52236"},{"dist": 81.8, "zip": "50278"},{"dist": 81.9, "zip": "50846"},{"dist": 81.9, "zip": "50859"},{"dist": 82.0, "zip": "63473"},{"dist": 82.2, "zip": "52217"},{"dist": 82.4, "zip": "52249"},{"dist": 82.9, "zip": "52354"},{"dist": 82.9, "zip": "64628"},{"dist": 82.9, "zip": "52322"},{"dist": 83.1, "zip": "64651"},{"dist": 83.3, "zip": "52203"},{"dist": 83.3, "zip": "50105"},{"dist": 83.3, "zip": "64631"},{"dist": 83.3, "zip": "52204"},{"dist": 83.4, "zip": "52619"},{"dist": 83.5, "zip": "50154"},{"dist": 83.5, "zip": "64499"},{"dist": 83.6, "zip": "50148"},{"dist": 83.8, "zip": "64647"},{"dist": 83.8, "zip": "52327"},{"dist": 84.0, "zip": "64659"},{"dist": 84.2, "zip": "50216"},{"dist": 84.4, "zip": "52659"},{"dist": 84.4, "zip": "63447"},{"dist": 84.4, "zip": "50862"},{"dist": 84.6, "zip": "50635"},{"dist": 84.7, "zip": "64402"},{"dist": 84.8, "zip": "50048"},{"dist": 84.8, "zip": "64688"},{"dist": 84.8, "zip": "50066"},{"dist": 84.9, "zip": "50236"},{"dist": 84.9, "zip": "63558"},{"dist": 85.1, "zip": "52656"},{"dist": 85.1, "zip": "64453"},{"dist": 85.4, "zip": "50036"},{"dist": 85.6, "zip": "52645"},{"dist": 85.7, "zip": "50099"},{"dist": 86.0, "zip": "52318"},{"dist": 86.1, "zip": "52644"},{"dist": 86.1, "zip": "50621"},{"dist": 86.1, "zip": "63464"},{"dist": 86.2, "zip": "50837"},{"dist": 86.3, "zip": "64657"},{"dist": 86.4, "zip": "64601"},{"dist": 86.4, "zip": "50609"},{"dist": 86.4, "zip": "52346"},{"dist": 86.5, "zip": "64670"},{"dist": 86.6, "zip": "63472"},{"dist": 86.7, "zip": "52340"},{"dist": 87.0, "zip": "50258"},{"dist": 87.1, "zip": "63534"},{"dist": 87.1, "zip": "50277"},{"dist": 87.6, "zip": "50248"},{"dist": 87.7, "zip": "52351"},{"dist": 87.8, "zip": "64658"},{"dist": 87.8, "zip": "63451"},{"dist": 88.1, "zip": "50841"},{"dist": 88.2, "zip": "50128"},{"dist": 88.3, "zip": "64486"},{"dist": 88.3, "zip": "64640"},{"dist": 88.5, "zip": "50212"},{"dist": 88.5, "zip": "63458"},{"dist": 88.8, "zip": "52737"},{"dist": 88.8, "zip": "50675"},{"dist": 88.9, "zip": "50235"},{"dist": 89.0, "zip": "50115"},{"dist": 89.3, "zip": "52315"},{"dist": 89.3, "zip": "52241"},{"dist": 89.3, "zip": "63532"},{"dist": 89.6, "zip": "63452"},{"dist": 89.6, "zip": "52738"},{"dist": 89.8, "zip": "64438"},{"dist": 90.0, "zip": "50206"},{"dist": 90.0, "zip": "50848"},{"dist": 90.2, "zip": "52660"},{"dist": 90.3, "zip": "50833"},{"dist": 90.5, "zip": "50002"},{"dist": 90.6, "zip": "52623"},{"dist": 90.6, "zip": "52224"},{"dist": 90.7, "zip": "64475"},{"dist": 90.9, "zip": "52246"},{"dist": 90.9, "zip": "52240"},{"dist": 90.9, "zip": "52242"},{"dist": 90.9, "zip": "52243"},{"dist": 90.9, "zip": "52245"},{"dist": 90.9, "zip": "52755"},{"dist": 91.0, "zip": "52639"},{"dist": 91.2, "zip": "50259"},{"dist": 91.2, "zip": "52317"},{"dist": 91.4, "zip": "63552"},{"dist": 91.4, "zip": "50853"},{"dist": 91.7, "zip": "52338"},{"dist": 91.7, "zip": "50059"},{"dist": 91.8, "zip": "64676"},{"dist": 92.0, "zip": "52228"},{"dist": 92.0, "zip": "52627"},{"dist": 92.0, "zip": "62354"},{"dist": 92.1, "zip": "50122"},{"dist": 92.1, "zip": "63457"},{"dist": 92.4, "zip": "63431"},{"dist": 92.4, "zip": "64681"},{"dist": 92.6, "zip": "52739"},{"dist": 92.6, "zip": "52229"},{"dist": 92.8, "zip": "50839"},{"dist": 92.8, "zip": "64664"},{"dist": 92.9, "zip": "50026"},{"dist": 93.0, "zip": "52206"},{"dist": 93.2, "zip": "64625"},{"dist": 93.5, "zip": "50612"},{"dist": 93.5, "zip": "52640"},{"dist": 93.5, "zip": "52638"},{"dist": 93.5, "zip": "63434"},{"dist": 93.6, "zip": "64620"},{"dist": 93.9, "zip": "63430"},{"dist": 94.0, "zip": "50230"},{"dist": 94.5, "zip": "64489"},{"dist": 94.7, "zip": "52632"},{"dist": 94.8, "zip": "50020"},{"dist": 94.9, "zip": "63437"},{"dist": 95.1, "zip": "50107"},{"dist": 95.1, "zip": "50223"},{"dist": 95.3, "zip": "50627"},{"dist": 95.3, "zip": "62379"},{"dist": 95.4, "zip": "50669"},{"dist": 95.5, "zip": "62358"},{"dist": 95.8, "zip": "50657"},{"dist": 95.8, "zip": "64479"},{"dist": 96.0, "zip": "50075"},{"dist": 96.1, "zip": "64660"},{"dist": 96.3, "zip": "64638"},{"dist": 96.3, "zip": "50638"},{"dist": 96.4, "zip": "52658"},{"dist": 96.5, "zip": "52766"},{"dist": 96.5, "zip": "50857"},{"dist": 96.6, "zip": "64643"},{"dist": 96.6, "zip": "64689"},{"dist": 96.7, "zip": "50130"},{"dist": 96.8, "zip": "50843"},{"dist": 97.0, "zip": "52349"},{"dist": 97.1, "zip": "52754"},{"dist": 97.2, "zip": "64461"},{"dist": 97.2, "zip": "63440"},{"dist": 97.2, "zip": "62341"},{"dist": 97.3, "zip": "63469"},{"dist": 97.4, "zip": "52227"},{"dist": 97.7, "zip": "50246"},{"dist": 97.7, "zip": "52653"},{"dist": 97.7, "zip": "64497"},{"dist": 97.8, "zip": "65247"},{"dist": 97.9, "zip": "52332"},{"dist": 98.0, "zip": "52637"},{"dist": 98.0, "zip": "50672"},{"dist": 98.2, "zip": "52333"},{"dist": 98.2, "zip": "52655"},{"dist": 98.2, "zip": "64656"},{"dist": 98.2, "zip": "50642"},{"dist": 98.6, "zip": "52650"},{"dist": 98.6, "zip": "50029"},{"dist": 98.7, "zip": "51646"},{"dist": 98.7, "zip": "52324"},{"dist": 98.8, "zip": "52497"},{"dist": 98.8, "zip": "52401"},{"dist": 98.8, "zip": "52404"},{"dist": 98.8, "zip": "52405"},{"dist": 98.8, "zip": "52402"},{"dist": 98.8, "zip": "52411"},{"dist": 98.8, "zip": "52403"},{"dist": 98.8, "zip": "64432"},{"dist": 98.8, "zip": "52498"},{"dist": 98.8, "zip": "52499"},{"dist": 98.9, "zip": "50129"},{"dist": 99.1, "zip": "63450"},{"dist": 99.1, "zip": "50064"},{"dist": 99.4, "zip": "64644"},{"dist": 99.4, "zip": "63435"},{"dist": 99.6, "zip": "64433"},{"dist": 99.7, "zip": "64434"},{"dist": 99.9, "zip": "50274"},{"dist": 99.9, "zip": "64649"},{"dist": 100.0, "zip": "50249"}]
