[{"dist": 14.6, "zip": "59754"},{"dist": 15.6, "zip": "59759"},{"dist": 19.1, "zip": "59749"},{"dist": 19.1, "zip": "59727"},{"dist": 20.4, "zip": "59721"},{"dist": 24.5, "zip": "59701"},{"dist": 24.8, "zip": "59750"},{"dist": 25.5, "zip": "59707"},{"dist": 27.5, "zip": "59762"},{"dist": 33.6, "zip": "59755"},{"dist": 38.0, "zip": "59745"},{"dist": 39.0, "zip": "59746"},{"dist": 40.1, "zip": "59632"},{"dist": 40.5, "zip": "59729"},{"dist": 43.7, "zip": "59711"},{"dist": 47.1, "zip": "59725"},{"dist": 48.2, "zip": "59752"},{"dist": 48.4, "zip": "59741"},{"dist": 51.7, "zip": "59641"},{"dist": 52.6, "zip": "59722"},{"dist": 53.4, "zip": "59736"},{"dist": 54.4, "zip": "59643"},{"dist": 55.6, "zip": "59720"},{"dist": 56.4, "zip": "59634"},{"dist": 57.4, "zip": "59718"},{"dist": 57.5, "zip": "59761"},{"dist": 59.4, "zip": "59714"},{"dist": 60.5, "zip": "59601"},{"dist": 64.9, "zip": "59730"},{"dist": 67.0, "zip": "59635"},{"dist": 67.4, "zip": "59625"},{"dist": 67.5, "zip": "59626"},{"dist": 67.7, "zip": "59623"},{"dist": 68.5, "zip": "59858"},{"dist": 68.7, "zip": "59731"},{"dist": 68.7, "zip": "59871"},{"dist": 69.4, "zip": "59715"},{"dist": 71.4, "zip": "59733"},{"dist": 71.9, "zip": "59739"},{"dist": 72.3, "zip": "59837"},{"dist": 73.4, "zip": "83462"},{"dist": 74.0, "zip": "83463"},{"dist": 75.3, "zip": "59644"},{"dist": 77.0, "zip": "59027"},{"dist": 78.4, "zip": "59602"},{"dist": 80.9, "zip": "59832"},{"dist": 80.9, "zip": "59065"},{"dist": 82.6, "zip": "59827"},{"dist": 82.9, "zip": "83466"},{"dist": 84.3, "zip": "59633"},{"dist": 85.5, "zip": "83467"},{"dist": 86.8, "zip": "59758"},{"dist": 87.3, "zip": "83446"},{"dist": 88.4, "zip": "59047"},{"dist": 88.6, "zip": "59825"},{"dist": 89.7, "zip": "59086"},{"dist": 89.9, "zip": "59828"},{"dist": 90.3, "zip": "59843"},{"dist": 91.0, "zip": "59645"},{"dist": 91.1, "zip": "59829"},{"dist": 91.2, "zip": "59030"},{"dist": 92.5, "zip": "59840"},{"dist": 92.8, "zip": "83429"},{"dist": 93.8, "zip": "83464"},{"dist": 98.7, "zip": "83423"},{"dist": 99.1, "zip": "59648"}]
