[{"dist": 4.6, "zip": "74735"},{"dist": 7.7, "zip": "74760"},{"dist": 8.0, "zip": "74743"},{"dist": 10.6, "zip": "74738"},{"dist": 12.0, "zip": "74562"},{"dist": 13.5, "zip": "75411"},{"dist": 14.4, "zip": "74755"},{"dist": 16.7, "zip": "74764"},{"dist": 18.3, "zip": "74759"},{"dist": 19.0, "zip": "74754"},{"dist": 19.1, "zip": "75412"},{"dist": 19.5, "zip": "75473"},{"dist": 20.0, "zip": "74523"},{"dist": 21.3, "zip": "74766"},{"dist": 22.7, "zip": "74543"},{"dist": 24.9, "zip": "75416"},{"dist": 25.1, "zip": "74736"},{"dist": 25.6, "zip": "75436"},{"dist": 26.0, "zip": "75486"},{"dist": 26.2, "zip": "74557"},{"dist": 26.4, "zip": "74567"},{"dist": 26.7, "zip": "75460"},{"dist": 26.7, "zip": "75462"},{"dist": 28.0, "zip": "74727"},{"dist": 31.8, "zip": "75468"},{"dist": 32.9, "zip": "74558"},{"dist": 33.1, "zip": "74745"},{"dist": 33.1, "zip": "75421"},{"dist": 33.7, "zip": "75426"},{"dist": 34.7, "zip": "75435"},{"dist": 36.6, "zip": "74728"},{"dist": 37.2, "zip": "75470"},{"dist": 37.4, "zip": "74724"},{"dist": 37.8, "zip": "74723"},{"dist": 38.7, "zip": "74536"},{"dist": 38.8, "zip": "75477"},{"dist": 39.2, "zip": "75488"},{"dist": 39.7, "zip": "75417"},{"dist": 39.9, "zip": "74555"},{"dist": 40.2, "zip": "75550"},{"dist": 40.8, "zip": "74540"},{"dist": 41.0, "zip": "75450"},{"dist": 41.8, "zip": "74574"},{"dist": 42.6, "zip": "74549"},{"dist": 43.0, "zip": "75446"},{"dist": 43.1, "zip": "74740"},{"dist": 44.1, "zip": "74726"},{"dist": 44.4, "zip": "75415"},{"dist": 45.8, "zip": "74734"},{"dist": 47.3, "zip": "75554"},{"dist": 47.6, "zip": "75481"},{"dist": 47.7, "zip": "75492"},{"dist": 48.1, "zip": "75487"},{"dist": 48.5, "zip": "75432"},{"dist": 48.5, "zip": "75476"},{"dist": 49.1, "zip": "75447"},{"dist": 49.2, "zip": "75469"},{"dist": 49.3, "zip": "74569"},{"dist": 50.0, "zip": "74525"},{"dist": 50.2, "zip": "74533"},{"dist": 50.8, "zip": "75438"},{"dist": 51.5, "zip": "74729"},{"dist": 51.6, "zip": "74957"},{"dist": 52.8, "zip": "75449"},{"dist": 53.0, "zip": "75448"},{"dist": 53.4, "zip": "74577"},{"dist": 53.8, "zip": "74571"},{"dist": 54.7, "zip": "74963"},{"dist": 54.9, "zip": "74560"},{"dist": 55.3, "zip": "74528"},{"dist": 55.5, "zip": "75418"},{"dist": 56.4, "zip": "74949"},{"dist": 56.5, "zip": "75559"},{"dist": 56.9, "zip": "74547"},{"dist": 57.0, "zip": "74553"},{"dist": 57.2, "zip": "74748"},{"dist": 57.3, "zip": "75478"},{"dist": 57.5, "zip": "75437"},{"dist": 57.7, "zip": "74576"},{"dist": 58.5, "zip": "74701"},{"dist": 58.7, "zip": "71842"},{"dist": 59.0, "zip": "71832"},{"dist": 59.3, "zip": "75457"},{"dist": 59.5, "zip": "74538"},{"dist": 59.9, "zip": "71866"},{"dist": 60.1, "zip": "71836"},{"dist": 60.3, "zip": "75439"},{"dist": 60.4, "zip": "75496"},{"dist": 61.0, "zip": "74730"},{"dist": 61.4, "zip": "71841"},{"dist": 61.5, "zip": "74741"},{"dist": 61.6, "zip": "74578"},{"dist": 61.9, "zip": "71944"},{"dist": 62.2, "zip": "71937"},{"dist": 62.3, "zip": "71973"},{"dist": 62.3, "zip": "75482"},{"dist": 62.4, "zip": "73432"},{"dist": 62.5, "zip": "75428"},{"dist": 62.5, "zip": "71972"},{"dist": 63.7, "zip": "75455"},{"dist": 64.1, "zip": "75479"},{"dist": 64.7, "zip": "73461"},{"dist": 65.0, "zip": "75558"},{"dist": 65.3, "zip": "71945"},{"dist": 65.3, "zip": "73449"},{"dist": 65.7, "zip": "75414"},{"dist": 65.8, "zip": "74733"},{"dist": 66.0, "zip": "74501"},{"dist": 66.0, "zip": "75420"},{"dist": 66.3, "zip": "74563"},{"dist": 66.5, "zip": "75431"},{"dist": 66.7, "zip": "75452"},{"dist": 66.9, "zip": "75433"},{"dist": 67.3, "zip": "75570"},{"dist": 68.1, "zip": "75574"},{"dist": 68.3, "zip": "74534"},{"dist": 68.3, "zip": "75491"},{"dist": 68.8, "zip": "71846"},{"dist": 69.0, "zip": "75423"},{"dist": 69.0, "zip": "75490"},{"dist": 69.0, "zip": "75571"},{"dist": 69.1, "zip": "73450"},{"dist": 69.2, "zip": "75471"},{"dist": 69.3, "zip": "75422"},{"dist": 69.5, "zip": "75568"},{"dist": 69.7, "zip": "74731"},{"dist": 70.4, "zip": "74939"},{"dist": 70.7, "zip": "75021"},{"dist": 70.7, "zip": "75020"},{"dist": 71.0, "zip": "75480"},{"dist": 72.0, "zip": "74572"},{"dist": 73.3, "zip": "74570"},{"dist": 73.4, "zip": "74529"},{"dist": 73.6, "zip": "75561"},{"dist": 74.1, "zip": "75494"},{"dist": 74.2, "zip": "71971"},{"dist": 74.4, "zip": "74937"},{"dist": 74.8, "zip": "75451"},{"dist": 74.9, "zip": "75686"},{"dist": 75.3, "zip": "74966"},{"dist": 75.6, "zip": "75566"},{"dist": 75.6, "zip": "75402"},{"dist": 75.6, "zip": "71822"},{"dist": 75.6, "zip": "75401"},{"dist": 75.7, "zip": "73460"},{"dist": 75.7, "zip": "74552"},{"dist": 75.7, "zip": "71953"},{"dist": 76.0, "zip": "75567"},{"dist": 76.0, "zip": "74561"},{"dist": 76.0, "zip": "75090"},{"dist": 76.0, "zip": "75092"},{"dist": 76.1, "zip": "75497"},{"dist": 76.2, "zip": "74940"},{"dist": 76.5, "zip": "75076"},{"dist": 77.3, "zip": "75424"},{"dist": 77.3, "zip": "73439"},{"dist": 77.9, "zip": "75638"},{"dist": 78.1, "zip": "71833"},{"dist": 78.3, "zip": "75453"},{"dist": 78.7, "zip": "74871"},{"dist": 79.2, "zip": "74944"},{"dist": 79.4, "zip": "75459"},{"dist": 80.2, "zip": "73446"},{"dist": 80.6, "zip": "75472"},{"dist": 80.8, "zip": "75495"},{"dist": 80.9, "zip": "74425"},{"dist": 81.6, "zip": "75409"},{"dist": 81.9, "zip": "74442"},{"dist": 81.9, "zip": "75442"},{"dist": 82.0, "zip": "74531"},{"dist": 82.0, "zip": "75560"},{"dist": 82.0, "zip": "74953"},{"dist": 82.1, "zip": "71853"},{"dist": 82.2, "zip": "75569"},{"dist": 82.4, "zip": "75135"},{"dist": 82.5, "zip": "75440"},{"dist": 82.9, "zip": "75656"},{"dist": 83.4, "zip": "74825"},{"dist": 83.7, "zip": "71851"},{"dist": 84.3, "zip": "74827"},{"dist": 84.6, "zip": "75668"},{"dist": 84.7, "zip": "75501"},{"dist": 84.7, "zip": "75599"},{"dist": 84.7, "zip": "75503"},{"dist": 84.7, "zip": "75507"},{"dist": 85.0, "zip": "75783"},{"dist": 85.3, "zip": "74472"},{"dist": 85.3, "zip": "74850"},{"dist": 85.8, "zip": "75454"},{"dist": 86.1, "zip": "74462"},{"dist": 86.2, "zip": "75410"},{"dist": 86.5, "zip": "74845"},{"dist": 86.6, "zip": "74956"},{"dist": 86.9, "zip": "74856"},{"dist": 87.0, "zip": "73447"},{"dist": 87.1, "zip": "75407"},{"dist": 87.1, "zip": "71859"},{"dist": 87.2, "zip": "74930"},{"dist": 87.2, "zip": "71852"},{"dist": 87.4, "zip": "76245"},{"dist": 87.4, "zip": "71854"},{"dist": 87.5, "zip": "76264"},{"dist": 88.0, "zip": "71959"},{"dist": 88.0, "zip": "75058"},{"dist": 88.2, "zip": "73440"},{"dist": 88.5, "zip": "74432"},{"dist": 88.7, "zip": "74941"},{"dist": 88.9, "zip": "75474"},{"dist": 89.4, "zip": "75173"},{"dist": 89.5, "zip": "71952"},{"dist": 89.5, "zip": "72938"},{"dist": 89.9, "zip": "74820"},{"dist": 90.3, "zip": "74932"},{"dist": 90.5, "zip": "72926"},{"dist": 90.8, "zip": "75563"},{"dist": 90.8, "zip": "71831"},{"dist": 91.2, "zip": "74843"},{"dist": 91.2, "zip": "75630"},{"dist": 91.2, "zip": "75189"},{"dist": 91.2, "zip": "74867"},{"dist": 91.4, "zip": "76273"},{"dist": 92.0, "zip": "74455"},{"dist": 92.1, "zip": "75166"},{"dist": 92.4, "zip": "75683"},{"dist": 92.5, "zip": "75644"},{"dist": 92.5, "zip": "75645"},{"dist": 92.8, "zip": "75572"},{"dist": 92.9, "zip": "75069"},{"dist": 92.9, "zip": "75070"},{"dist": 92.9, "zip": "75071"},{"dist": 93.4, "zip": "74848"},{"dist": 93.5, "zip": "74865"},{"dist": 93.8, "zip": "75551"},{"dist": 93.9, "zip": "71838"},{"dist": 94.1, "zip": "74839"},{"dist": 94.1, "zip": "75773"},{"dist": 94.1, "zip": "76233"},{"dist": 94.3, "zip": "75098"},{"dist": 94.3, "zip": "75009"},{"dist": 94.4, "zip": "74461"},{"dist": 94.4, "zip": "72958"},{"dist": 94.7, "zip": "74959"},{"dist": 95.3, "zip": "75140"},{"dist": 95.8, "zip": "75127"},{"dist": 95.9, "zip": "71855"},{"dist": 95.9, "zip": "72944"},{"dist": 96.2, "zip": "76271"},{"dist": 96.2, "zip": "71958"},{"dist": 96.4, "zip": "75117"},{"dist": 96.6, "zip": "72940"},{"dist": 96.9, "zip": "72937"},{"dist": 97.1, "zip": "73086"},{"dist": 97.3, "zip": "75078"},{"dist": 97.4, "zip": "74883"},{"dist": 97.7, "zip": "75556"},{"dist": 97.7, "zip": "75013"},{"dist": 97.7, "zip": "75002"},{"dist": 98.1, "zip": "75169"},{"dist": 98.2, "zip": "75032"},{"dist": 98.2, "zip": "75087"},{"dist": 98.4, "zip": "71862"},{"dist": 98.5, "zip": "74902"},{"dist": 99.2, "zip": "75765"},{"dist": 99.4, "zip": "71847"},{"dist": 99.7, "zip": "71961"}]
