[{"dist": 5.7, "zip": "82301"},{"dist": 27.0, "zip": "82331"},{"dist": 29.5, "zip": "82327"},{"dist": 42.7, "zip": "82325"},{"dist": 47.5, "zip": "82329"},{"dist": 49.1, "zip": "82332"},{"dist": 55.5, "zip": "81653"},{"dist": 55.5, "zip": "82323"},{"dist": 57.4, "zip": "82620"},{"dist": 58.2, "zip": "82321"},{"dist": 58.8, "zip": "82083"},{"dist": 61.1, "zip": "82615"},{"dist": 61.6, "zip": "82310"},{"dist": 74.4, "zip": "82051"},{"dist": 74.5, "zip": "80428"},{"dist": 76.0, "zip": "82063"},{"dist": 81.0, "zip": "82058"},{"dist": 83.6, "zip": "82609"},{"dist": 83.6, "zip": "82604"},{"dist": 83.6, "zip": "82601"},{"dist": 83.7, "zip": "80480"},{"dist": 85.2, "zip": "82072"},{"dist": 85.2, "zip": "82070"},{"dist": 87.7, "zip": "82636"},{"dist": 88.3, "zip": "82646"},{"dist": 89.3, "zip": "81625"},{"dist": 89.4, "zip": "81639"},{"dist": 90.1, "zip": "80430"},{"dist": 91.0, "zip": "80487"},{"dist": 94.0, "zip": "82638"},{"dist": 97.7, "zip": "82630"},{"dist": 98.5, "zip": "82637"},{"dist": 100.0, "zip": "81640"},{"dist": 100.0, "zip": "81638"}]
